{
  "resolvedId": "/Users/jiyankang/vscodeProjects/witque-blog/node_modules/.pnpm/@nuxt-themes+typography@0.11.0_rollup@3.29.3_vue@3.4.15/node_modules/@nuxt-themes/typography/components/global/ProseUl.vue?vue&type=style&index=0&scoped=7fe5e2e4&transformed=true&lang.postcss",
  "transforms": [
    {
      "name": "pinceau-transforms",
      "result": "ul{font-family:var(--typography-font-body);list-style-type:var(--prose-ul-listStyleType);padding-inline-start:var(--prose-ul-paddingInlineStart);margin:var(--prose-ul-margin);}ul > :deep(li)::marker{color:var(--prose-ul-li-markerColor);}ul > :deep(li) ul,ul > :deep(li) ol{margin:0;}",
      "start": 1774875881226,
      "end": 1774875881226,
      "sourcemaps": {
        "version": 3,
        "file": "/Users/jiyankang/vscodeProjects/witque-blog/node_modules/.pnpm/@nuxt-themes+typography@0.11.0_rollup@3.29.3_vue@3.4.15/node_modules/@nuxt-themes/typography/components/global/ProseUl.vue",
        "sources": [
          "/Users/jiyankang/vscodeProjects/witque-blog/node_modules/.pnpm/@nuxt-themes+typography@0.11.0_rollup@3.29.3_vue@3.4.15/node_modules/@nuxt-themes/typography/components/global/ProseUl.vue"
        ],
        "sourcesContent": [
          "ul{font-family:var(--typography-font-body);list-style-type:var(--prose-ul-listStyleType);padding-inline-start:var(--prose-ul-paddingInlineStart);margin:var(--prose-ul-margin);}ul > :deep(li)::marker{color:var(--prose-ul-li-markerColor);}ul > :deep(li) ul,ul > :deep(li) ol{margin:0;}"
        ],
        "names": [],
        "mappings": "AAAA"
      }
    },
    {
      "name": "nuxt:layer-aliasing",
      "start": 1774875881227,
      "end": 1774875881227,
      "order": "pre"
    },
    {
      "name": "nuxt:layer-aliasing",
      "start": 1774875881227,
      "end": 1774875881227,
      "order": "pre"
    },
    {
      "name": "nuxt:server-devonly:transform",
      "start": 1774875881228,
      "end": 1774875881228,
      "order": "pre"
    },
    {
      "name": "nuxt:server-devonly:transform",
      "start": 1774875881228,
      "end": 1774875881228,
      "order": "pre"
    },
    {
      "name": "pinceau-transforms",
      "result": "ul{font-family:var(--typography-font-body);list-style-type:var(--prose-ul-listStyleType);padding-inline-start:var(--prose-ul-paddingInlineStart);margin:var(--prose-ul-margin);}ul > :deep(li)::marker{color:var(--prose-ul-li-markerColor);}ul > :deep(li) ul,ul > :deep(li) ol{margin:0;}",
      "start": 1774875881228,
      "end": 1774875881228,
      "order": "pre"
    },
    {
      "name": "pinceau-transforms",
      "result": "ul{font-family:var(--typography-font-body);list-style-type:var(--prose-ul-listStyleType);padding-inline-start:var(--prose-ul-paddingInlineStart);margin:var(--prose-ul-margin);}ul > :deep(li)::marker{color:var(--prose-ul-li-markerColor);}ul > :deep(li) ul,ul > :deep(li) ol{margin:0;}",
      "start": 1774875881228,
      "end": 1774875881228,
      "order": "pre"
    },
    {
      "name": "content-slot",
      "start": 1774875881229,
      "end": 1774875881229,
      "order": "pre"
    },
    {
      "name": "content-slot",
      "start": 1774875881229,
      "end": 1774875881229,
      "order": "pre"
    },
    {
      "name": "nuxt:client-fallback-auto-id",
      "start": 1774875881229,
      "end": 1774875881230,
      "order": "pre"
    },
    {
      "name": "vite:css",
      "result": "ul{font-family:var(--typography-font-body);list-style-type:var(--prose-ul-listStyleType);margin:var(--prose-ul-margin);padding-inline-start:var(--prose-ul-paddingInlineStart)}ul>:deep(li)::marker{color:var(--prose-ul-li-markerColor)}ul>:deep(li) ol,ul>:deep(li) ul{margin:0}",
      "start": 1774875881230,
      "end": 1774875881232,
      "order": "normal",
      "sourcemaps": {
        "file": "/Users/jiyankang/vscodeProjects/witque-blog/node_modules/.pnpm/@nuxt-themes+typography@0.11.0_rollup@3.29.3_vue@3.4.15/node_modules/@nuxt-themes/typography/components/global/ProseUl.vue",
        "mappings": "AAAA,GAAG,uCAAuC,CAAC,6CAA6C,CAAyD,6BAA6B,CAArF,uDAAsF,CAAC,qBAAuB,oCAAqC,CAAC,gCAAoC,QAAS",
        "names": [],
        "sources": [
          "/Users/jiyankang/vscodeProjects/witque-blog/node_modules/.pnpm/@nuxt-themes+typography@0.11.0_rollup@3.29.3_vue@3.4.15/node_modules/@nuxt-themes/typography/components/global/ProseUl.vue"
        ],
        "sourcesContent": [
          "ul{font-family:var(--typography-font-body);list-style-type:var(--prose-ul-listStyleType);padding-inline-start:var(--prose-ul-paddingInlineStart);margin:var(--prose-ul-margin);}ul > :deep(li)::marker{color:var(--prose-ul-li-markerColor);}ul > :deep(li) ul,ul > :deep(li) ol{margin:0;}"
        ],
        "version": 3
      }
    },
    {
      "name": "vite:esbuild",
      "start": 1774875881232,
      "end": 1774875881232,
      "order": "normal"
    },
    {
      "name": "vite:json",
      "start": 1774875881232,
      "end": 1774875881232,
      "order": "normal"
    },
    {
      "name": "vite:worker",
      "start": 1774875881232,
      "end": 1774875881232,
      "order": "normal"
    },
    {
      "name": "vite:vue",
      "result": "ul[data-v-7fe5e2e4]{font-family:var(--typography-font-body);list-style-type:var(--prose-ul-listStyleType);margin:var(--prose-ul-margin);padding-inline-start:var(--prose-ul-paddingInlineStart)}ul[data-v-7fe5e2e4]> li::marker{color:var(--prose-ul-li-markerColor)}ul[data-v-7fe5e2e4]> li ol,ul[data-v-7fe5e2e4]> li ul{margin:0}",
      "start": 1774875881232,
      "end": 1774875881233,
      "order": "normal",
      "sourcemaps": {
        "file": "/Users/jiyankang/vscodeProjects/witque-blog/node_modules/.pnpm/@nuxt-themes+typography@0.11.0_rollup@3.29.3_vue@3.4.15/node_modules/@nuxt-themes/typography/components/global/ProseUl.vue",
        "mappings": "AAAA,oBAAG,uCAAuC,CAAC,6CAA6C,CAAC,6BAA6B,CAAC,uDAAuD,CAAC,gCAAqB,oCAAoC,CAAC,sDAAgC,QAAQ",
        "names": [],
        "sources": [
          "/Users/jiyankang/vscodeProjects/witque-blog/node_modules/.pnpm/@nuxt-themes+typography@0.11.0_rollup@3.29.3_vue@3.4.15/node_modules/@nuxt-themes/typography/components/global/ProseUl.vue"
        ],
        "sourcesContent": [
          null
        ],
        "version": 3
      }
    },
    {
      "name": "vite:vue-jsx",
      "start": 1774875881233,
      "end": 1774875881233,
      "order": "normal"
    },
    {
      "name": "replace",
      "start": 1774875881233,
      "end": 1774875881233,
      "order": "normal"
    },
    {
      "name": "replace",
      "start": 1774875881233,
      "end": 1774875881233,
      "order": "normal"
    },
    {
      "name": "nuxt:remove-plugin-metadata",
      "start": 1774875881233,
      "end": 1774875881234,
      "order": "normal"
    },
    {
      "name": "nuxt:remove-plugin-metadata",
      "start": 1774875881233,
      "end": 1774875881234,
      "order": "normal"
    },
    {
      "name": "nuxt:components:imports",
      "start": 1774875881234,
      "end": 1774875881234,
      "order": "normal"
    },
    {
      "name": "replace",
      "start": 1774875881234,
      "end": 1774875881234,
      "order": "normal"
    },
    {
      "name": "ssr-styles",
      "start": 1774875881234,
      "end": 1774875881235,
      "order": "normal"
    },
    {
      "name": "vite:define",
      "start": 1774875881235,
      "end": 1774875881235,
      "order": "normal"
    },
    {
      "name": "vite:css-post",
      "result": "",
      "start": 1774875881235,
      "end": 1774875881235,
      "order": "normal",
      "sourcemaps": {
        "mappings": ""
      }
    },
    {
      "name": "vite:build-html",
      "start": 1774875881235,
      "end": 1774875881235,
      "order": "normal"
    },
    {
      "name": "vite:worker-import-meta-url",
      "start": 1774875881235,
      "end": 1774875881235,
      "order": "normal"
    },
    {
      "name": "vite:asset-import-meta-url",
      "start": 1774875881235,
      "end": 1774875881235,
      "order": "normal"
    },
    {
      "name": "commonjs",
      "start": 1774875881235,
      "end": 1774875881235,
      "order": "normal"
    },
    {
      "name": "vite:dynamic-import-vars",
      "start": 1774875881235,
      "end": 1774875881235,
      "order": "normal"
    },
    {
      "name": "vite:import-glob",
      "start": 1774875881235,
      "end": 1774875881235,
      "order": "normal"
    },
    {
      "name": "nuxt:composable-keys",
      "start": 1774875881235,
      "end": 1774875881235,
      "order": "post"
    },
    {
      "name": "nuxt:composable-keys",
      "start": 1774875881235,
      "end": 1774875881235,
      "order": "post"
    },
    {
      "name": "nuxt:imports-transform",
      "start": 1774875881235,
      "end": 1774875881235,
      "order": "post"
    },
    {
      "name": "nuxt:imports-transform",
      "start": 1774875881235,
      "end": 1774875881235,
      "order": "post"
    },
    {
      "name": "unctx:transform",
      "start": 1774875881235,
      "end": 1774875881235,
      "order": "post"
    },
    {
      "name": "unctx:transform",
      "start": 1774875881235,
      "end": 1774875881235,
      "order": "post"
    },
    {
      "name": "nuxt:pages-macros-transform",
      "start": 1774875881235,
      "end": 1774875881236,
      "order": "post"
    },
    {
      "name": "nuxt:pages-macros-transform",
      "start": 1774875881235,
      "end": 1774875881236,
      "order": "post"
    },
    {
      "name": "nuxt:tree-shake-template",
      "start": 1774875881236,
      "end": 1774875881236,
      "order": "post"
    },
    {
      "name": "nuxt:components-loader",
      "start": 1774875881236,
      "end": 1774875881236,
      "order": "post"
    },
    {
      "name": "nuxt:tree-shake-composables:transform",
      "start": 1774875881236,
      "end": 1774875881236,
      "order": "post"
    },
    {
      "name": "vite:build-import-analysis",
      "start": 1774875881236,
      "end": 1774875881236,
      "order": "normal"
    },
    {
      "name": "vite:reporter",
      "start": 1774875881236,
      "end": 1774875881236,
      "order": "normal"
    }
  ]
}
